library/__init__.py
library/asciirt.py
asciirt-0.0.3.dist-info/LICENSE
asciirt-0.0.3.dist-info/METADATA
asciirt-0.0.3.dist-info/WHEEL
asciirt-0.0.3.dist-info/top_level.txt
asciirt-0.0.3.dist-info/RECORD
