Metadata-Version: 2.1
Name: asciirt
Version: 0.0.3
Summary: Ascii Art easier than ever.
Home-page: UNKNOWN
Author: Arxify (Daniel Rodriguez)
Author-email: <arxifybusiness@proton.me>
License: UNKNOWN
Keywords: python,ascii,art,colours,colors,text,unicode
Platform: UNKNOWN
Classifier: Development Status :: 1 - Planning
Classifier: Intended Audience :: Developers
Classifier: Programming Language :: Python :: 3
Classifier: Operating System :: Unix
Classifier: Operating System :: MacOS :: MacOS X
Classifier: Operating System :: Microsoft :: Windows
License-File: LICENSE
Requires-Dist: colorama
